ofenaus/LICENSE
ofenaus/README.MD
ofenaus/__init__.py
ofenaus/requirements.txt
ofenaus/thirdparty.json
ofenaus-0.11.dist-info/LICENSE.rst
ofenaus-0.11.dist-info/METADATA
ofenaus-0.11.dist-info/WHEEL
ofenaus-0.11.dist-info/top_level.txt
ofenaus-0.11.dist-info/RECORD
