Metadata-Version: 2.1
Name: ofenaus
Version: 0.11
Summary: Timeout decorator for functions! Works on Windows with multiprocessing, threading, subprocess!
Home-page: https://github.com/hansalemaos/ofenaus
Author: Johannes Fischer
Author-email: <aulasparticularesdealemaosp@gmail.com>
License: MIT
Keywords: windows,decorator,timeout
Classifier: Development Status :: 4 - Beta
Classifier: Programming Language :: Python :: 3 :: Only
Classifier: Programming Language :: Python :: 3.9
Classifier: Topic :: Scientific/Engineering :: Visualization
Classifier: Topic :: Software Development :: Libraries :: Python Modules
Classifier: Topic :: Text Editors :: Text Processing
Classifier: Topic :: Text Processing :: General
Classifier: Topic :: Text Processing :: Indexing
Classifier: Topic :: Text Processing :: Filters
Classifier: Topic :: Utilities
License-File: LICENSE.rst
Requires-Dist: copy-functions-and-more
Requires-Dist: kthread
Requires-Dist: psutil
